{
    "timestamp": "2025-04-27 04:28:52",
    "all_news": [
        {
            "title": "Elon Musk’s xAI Seeks $20B Funding Round",
            "translated_facebook_post": "Skipped",
            "translated_title": "",
            "translated_content": "",
            "translated_summary": "",
            "original_url": "https://coinmarketcap.com/community/en/articles/680daf64646f146f2352dafa",
            "source": "Kanal Coin",
            "image": "https://www.kanalcoin.com/wp-content/uploads/2025/04/elon-musk-in-office-meeting.png",
            "fb_status": "Skipped",
            "wp_status": "Skipped",
            "timestamp": "2025-04-27 04:10:00"
        },
        {
            "title": "Institutional Interest Grows as Bitcoin ETFs Hit New Inflow Milestone",
            "translated_facebook_post": "Skipped",
            "translated_title": "",
            "translated_content": "",
            "translated_summary": "",
            "original_url": "https://coinmarketcap.com/community/en/articles/680dae17524adc35bb61c29e",
            "source": "Coindoo",
            "image": "https://coindoo.com/wp-content/uploads/2025/04/bitcoin-btc-etf.jpg",
            "fb_status": "Skipped",
            "wp_status": "Skipped",
            "timestamp": "2025-04-27 04:05:00"
        },
        {
            "title": "Potential Solana Breakout Eyed for $296 Surge",
            "translated_facebook_post": "Skipped",
            "translated_title": "",
            "translated_content": "",
            "translated_summary": "",
            "original_url": "https://coinmarketcap.com/community/en/articles/680dae12646f146f2352daf6",
            "source": "Bitcoin Info News",
            "image": "https://bitcoininfonews.com/wp-content/uploads/2025/04/solana-price-chart-retro-game.png.jpg",
            "fb_status": "Skipped",
            "wp_status": "Skipped",
            "timestamp": "2025-04-27 04:05:00"
        },
        {
            "title": "Ken Griffin Criticizes U.S. Tariff Strategy",
            "translated_facebook_post": "Skipped",
            "translated_title": "",
            "translated_content": "",
            "translated_summary": "",
            "original_url": "https://coinmarketcap.com/community/en/articles/680dacddf868752fd8c3d1d5",
            "source": "TheCCPress",
            "image": "https://theccpress.com/wp-content/uploads/2025/04/ken-griffin-thoughtful-pose.png",
            "fb_status": "Skipped",
            "wp_status": "Skipped",
            "timestamp": "2025-04-27 04:03:00"
        },
        {
            "title": "BlockDAG, Dragoin, & Unstaked: Why These 6 Projects Are Heating Up the Best Presale Crypto List",
            "translated_facebook_post": "Beberapa projek kripto pra-jualan menarik perhatian sekarang, antaranya BlockDAG dengan harga rendah dan pulangan pelaburan yang tinggi, Dragoin yang gabungkan unsur permainan dan meme, Web3 ai serta Web3Bay yang guna teknologi AI untuk pelaburan, Unstaked yang membolehkan bina komuniti AI, dan Cold Wallet yang fokus pada keselamatan kripto.  Peluang ini mungkin tak lama, jadi kena cepat bertindak.",
            "translated_title": "",
            "translated_content": "",
            "translated_summary": "",
            "original_url": "https://coinmarketcap.com/community/en/articles/680d3660f310ff328dcd255f",
            "source": "Crypto Economy",
            "image": "https://academy-public.coinmarketcap.com/srd-optimized-uploads/ec4cc2a9cc43442884ef5505ea48003a.png",
            "fb_status": "Posted",
            "wp_status": "Skipped",
            "timestamp": "2025-04-27 04:02:00"
        },
        {
            "title": "Best Cryptos to Watch Now: Pi Network, PEPE, POPCAT, & BlockDAG Make Bold Moves in April",
            "translated_facebook_post": "Skipped",
            "translated_title": "",
            "translated_content": "",
            "translated_summary": "",
            "original_url": "https://coinmarketcap.com/community/en/articles/680dacdc622da00de1164e45",
            "source": "Coindoo",
            "image": "https://coindoo.com/wp-content/uploads/2025/04/IMAGE-2025-04-27-041023.jpg",
            "fb_status": "Skipped",
            "wp_status": "Skipped",
            "timestamp": "2025-04-27 04:00:00"
        },
        {
            "title": "Best Long Term Cryptos for 2025: Polygon, Kaspa, Stacks, Cardano, and BlockDAG Show Strength",
            "translated_facebook_post": "Skipped",
            "translated_title": "",
            "translated_content": "",
            "translated_summary": "",
            "original_url": "https://coinmarketcap.com/community/en/articles/680dacdd622da00de1164e47",
            "source": "TokenTopNews",
            "image": "https://tokentopnews.com/wp-content/uploads/2025/04/2025-04-26T170328.458Zunnamed.png",
            "fb_status": "Skipped",
            "wp_status": "Skipped",
            "timestamp": "2025-04-27 04:00:00"
        },
        {
            "title": "Best Long Term Cryptos: Stacks, Cardano, Solana, and BlockDAG Could Lead 2025 Gains",
            "translated_facebook_post": "Skipped",
            "translated_title": "",
            "translated_content": "",
            "translated_summary": "",
            "original_url": "https://coinmarketcap.com/community/en/articles/680dacdd646f146f2352daf0",
            "source": "Kanal Coin",
            "image": "https://www.kanalcoin.com/wp-content/uploads/2025/04/2025-04-26T163256.440Zunnamed.png",
            "fb_status": "Skipped",
            "wp_status": "Skipped",
            "timestamp": "2025-04-27 04:00:00"
        },
        {
            "title": "Best Cryptos to Accumulate in April: Helium, Hedera, Trump, and BlockDAG Show Strong Upside",
            "translated_facebook_post": "Skipped",
            "translated_title": "",
            "translated_content": "",
            "translated_summary": "",
            "original_url": "https://coinmarketcap.com/community/en/articles/680dacddf868752fd8c3d1d7",
            "source": "TheCCPress",
            "image": "https://theccpress.com/wp-content/uploads/2025/04/2025-04-26T164314.175Zunnamed.png",
            "fb_status": "Skipped",
            "wp_status": "Skipped",
            "timestamp": "2025-04-27 04:00:00"
        },
        {
            "title": "Top Trending Crypto in April: SUI, Dogwifhat, Fartcoin, and BlockDAG Fuel Market Momentum",
            "translated_facebook_post": "Skipped",
            "translated_title": "",
            "translated_content": "",
            "translated_summary": "",
            "original_url": "https://coinmarketcap.com/community/en/articles/680dacdd646f146f2352daf2",
            "source": "Bitcoin Info News",
            "image": "https://bitcoininfonews.com/wp-content/uploads/2025/04/2025-04-26T162745.043Zunnamed.png",
            "fb_status": "Skipped",
            "wp_status": "Skipped",
            "timestamp": "2025-04-27 04:00:00"
        },
        {
            "title": "Ethereum, XRP, & BlockDAG: Comparing Price Trends & Strategic Moves",
            "translated_facebook_post": "Skipped",
            "translated_title": "",
            "translated_content": "",
            "translated_summary": "",
            "original_url": "https://coinmarketcap.com/community/en/articles/680dacdef868752fd8c3d1d9",
            "source": "CoinLive.me",
            "image": "https://coinlive.me/wp-content/uploads/2025/04/image-11.png",
            "fb_status": "Skipped",
            "wp_status": "Skipped",
            "timestamp": "2025-04-27 04:00:00"
        },
        {
            "title": "BlockDAG Rolls Back to $0.0025, ALGO Hits Resistance, & OM Token Crash Shocks Traders",
            "translated_facebook_post": "Skipped",
            "translated_title": "",
            "translated_content": "",
            "translated_summary": "",
            "original_url": "https://coinmarketcap.com/community/en/articles/680dacdf646f146f2352daf4",
            "source": "CoinLineup",
            "image": "https://coinlineup.com/wp-content/uploads/2025/04/2025-04-26T170947.290Zunnamed.png",
            "fb_status": "Skipped",
            "wp_status": "Skipped",
            "timestamp": "2025-04-27 04:00:00"
        },
        {
            "title": "Binance Futures Volume Surpasses $1 Trillion Milestone",
            "translated_facebook_post": "Skipped",
            "translated_title": "",
            "translated_content": "",
            "translated_summary": "",
            "original_url": "https://coinmarketcap.com/community/en/articles/680dab9ef868752fd8c3d1d2",
            "source": "CoinLive.me",
            "image": "https://coinlive.me/wp-content/uploads/2025/04/futuristic-crypto-trading-floor.png",
            "fb_status": "Skipped",
            "wp_status": "Skipped",
            "timestamp": "2025-04-27 03:58:00"
        },
        {
            "title": "Bitcoin Futures Signal Possible Record with Negative Funding",
            "translated_facebook_post": "Skipped",
            "translated_title": "",
            "translated_content": "",
            "translated_summary": "",
            "original_url": "https://coinmarketcap.com/community/en/articles/680dab9e622da00de1164e43",
            "source": "CoinLineup",
            "image": "https://coinlineup.com/wp-content/uploads/2025/04/bitcoin-funding-rates-analysis.png",
            "fb_status": "Skipped",
            "wp_status": "Skipped",
            "timestamp": "2025-04-27 03:58:00"
        },
        {
            "title": "Kevin Warsh Criticizes Federal Reserve's Communication Practices",
            "translated_facebook_post": "Skipped",
            "translated_title": "",
            "translated_content": "",
            "translated_summary": "",
            "original_url": "https://coinmarketcap.com/community/en/articles/680daa89524adc35bb61c29c",
            "source": "Coincu",
            "image": "https://coincu.com/wp-content/uploads/2025/04/kevin-warsh-federal-critique.png",
            "fb_status": "Skipped",
            "wp_status": "Skipped",
            "timestamp": "2025-04-27 03:51:00"
        },
        {
            "title": "Musk's xAI Pursues $20 Billion Funding",
            "translated_facebook_post": "Skipped",
            "translated_title": "",
            "translated_content": "",
            "translated_summary": "",
            "original_url": "https://coinmarketcap.com/community/en/articles/680da958f868752fd8c3d1ce",
            "source": "Kanal Coin",
            "image": "https://www.kanalcoin.com/wp-content/uploads/2025/04/elon-musk-modern-office-scene.png",
            "fb_status": "Skipped",
            "wp_status": "Skipped",
            "timestamp": "2025-04-27 03:48:00"
        },
        {
            "title": "Dogecoin Nears Wyckoff Phase E as Breakout Signals Grow Stronger",
            "translated_facebook_post": "Skipped",
            "translated_title": "",
            "translated_content": "",
            "translated_summary": "",
            "original_url": "https://coinmarketcap.com/community/en/articles/680da957646f146f2352daed",
            "source": "Crypto Front News",
            "image": "https://cryptofrontnews.com/wp-content/uploads/2024/11/dogecoin-1-2.jpg",
            "fb_status": "Skipped",
            "wp_status": "Skipped",
            "timestamp": "2025-04-27 03:45:00"
        },
        {
            "title": "Can This Pattern Breakout Launch Solana Price To $296 Next?",
            "translated_facebook_post": "Skipped",
            "translated_title": "",
            "translated_content": "",
            "translated_summary": "",
            "original_url": "https://coinmarketcap.com/community/en/articles/680da95b622da00de1164e40",
            "source": "The Coin Republic",
            "image": "https://www.thecoinrepublic.com/wp-content/uploads/2025/04/46645b1983b0445c8399b780d3e81876.jpeg",
            "fb_status": "Skipped",
            "wp_status": "Skipped",
            "timestamp": "2025-04-27 03:45:00"
        },
        {
            "title": "Binance's Zhao Proposes User-Driven Token Listings",
            "translated_facebook_post": "Skipped",
            "translated_title": "",
            "translated_content": "",
            "translated_summary": "",
            "original_url": "https://coinmarketcap.com/community/en/articles/680da82e524adc35bb61c29a",
            "source": "Bitcoin Info News",
            "image": "https://bitcoininfonews.com/wp-content/uploads/2025/04/changpeng-zhao-pixel-art-office.jpg",
            "fb_status": "Skipped",
            "wp_status": "Skipped",
            "timestamp": "2025-04-27 03:42:00"
        },
        {
            "title": "Ripple Boosts RLUSD Supply with 23 Million Mint Ahead of Aave Listing",
            "translated_facebook_post": "Skipped",
            "translated_title": "",
            "translated_content": "",
            "translated_summary": "",
            "original_url": "https://coinmarketcap.com/community/en/articles/680da831646f146f2352daea",
            "source": "ETHNews.com",
            "image": "https://www.ethnews.com/wp-content/uploads/2025/01/Ripple-Empowers-Central-Banks-With-Groundbreaking-CBDC-Platform.jpeg",
            "fb_status": "Skipped",
            "wp_status": "Skipped",
            "timestamp": "2025-04-27 03:42:00"
        }
    ]
}