{
    "timestamp": "2025-04-23 20:30:17",
    "all_news": [
        {
            "title": "Coinbase Exec Says Bitcoin Gains Attention Post-Gold Rally",
            "translated_facebook_post": "Ramai pelabur mula berminat dengan Bitcoin lepas emas naik harga, jadi Bitcoin dilihat sebagai pelaburan alternatif yang menarik.",
            "translated_title": "",
            "translated_content": "",
            "translated_summary": "",
            "original_url": "https://coinmarketcap.com/community/en/articles/68094b6672206e3424b974a1",
            "source": "Bitcoin Info News",
            "image": "https://bitcoininfonews.com/wp-content/uploads/2025/04/coinbase-executive-pixel-art-report.jpg",
            "fb_status": "Posted",
            "wp_status": "Skipped",
            "timestamp": "2025-04-23 20:17:00"
        },
        {
            "title": "Polygon Labs Brings Electric Motorcycles On-Chain in Dubai",
            "translated_facebook_post": "Polygon Labs dan Pyse bekerjasama di Dubai, guna teknologi blockchain untuk jejak motosikal elektrik penghantaran,  kumpul data kualiti udara, keadaan jalan, dan pencemaran bunyi,  serta memberi ganjaran token kepada penyumbang data.  Projek ini dirancang untuk dikembangkan ke India seterusnya.",
            "translated_title": "",
            "translated_content": "",
            "translated_summary": "",
            "original_url": "https://coinmarketcap.com/community/en/articles/68094b664eea9e3b10a482f5",
            "source": "Coindoo",
            "image": "https://coindoo.com/wp-content/uploads/2021/08/polygon-1.jpg",
            "fb_status": "Posted",
            "wp_status": "Skipped",
            "timestamp": "2025-04-23 20:16:00"
        },
        {
            "title": "Dow, S&P 500, Nasdaq end in green as Trump softens on China talk",
            "translated_facebook_post": "Pasaran saham Amerika naik sebab Trump bagi isyarat kurang tegas pasal tarif China dan takkan pecat ketua Rizab Persekutuan, lega sikit la pelabur.",
            "translated_title": "",
            "translated_content": "",
            "translated_summary": "",
            "original_url": "https://coinmarketcap.com/community/en/articles/68094b654eea9e3b10a482f1",
            "source": "crypto.news",
            "image": "https://crypto.news/app/uploads/2025/03/crypto-news-Nasdaq-option04.webp",
            "fb_status": "Posted",
            "wp_status": "Skipped",
            "timestamp": "2025-04-23 20:15:00"
        },
        {
            "title": "May 26 Deadline Looms for BTFD’s Presale — PENGU Trading Volume Soars, MELANIA Sees Fresh Spike: Which Is the Next Crypto To Explode?",
            "translated_facebook_post": "Beberapa duit kripto, macam BTFD, PENGU, dan MELANIA tengah naik sekarang. BTFD nampaknya paling menarik sebab presale dia dah nak habis, ada ganjaran tinggi, dan ramai orang seronok dengan dia.  Cepatlah sikit kalau nak sertai!",
            "translated_title": "",
            "translated_content": "",
            "translated_summary": "",
            "original_url": "https://coinmarketcap.com/community/en/articles/68094b6528babe4022001dfe",
            "source": "Coindoo",
            "image": "https://coindoo.com/wp-content/uploads/2025/04/btfd-cow-chance-1.webp",
            "fb_status": "Posted",
            "wp_status": "Skipped",
            "timestamp": "2025-04-23 20:15:00"
        },
        {
            "title": "Dragoin’s Telegram Game Goes Live & 6,700% ROI Potential Outshine PEPE’s Prediction & XRP’s Volatility",
            "translated_facebook_post": "Pada April 2025,  pelaburan dalam  crypto nampak macam bercampur-baur.  Dragoin menawarkan permainan dan potensi pulangan yang menarik berbanding  kejayaan PEPE dan XRP yang kurang pasti.",
            "translated_title": "",
            "translated_content": "",
            "translated_summary": "",
            "original_url": "https://coinmarketcap.com/community/en/articles/68094b667416902e68361056",
            "source": "36Crypto",
            "image": "https://i0.wp.com/36crypto.com/wp-content/uploads/2025/04/image4-convert.io-2025-04-23T172807.896.webp",
            "fb_status": "Posted",
            "wp_status": "Skipped",
            "timestamp": "2025-04-23 20:15:00"
        },
        {
            "title": "VeChain price prediction 2025-2031: What’s the growth potential of VET?",
            "translated_facebook_post": "Ramalan harga VeChain menunjukkan potensi kenaikan sehingga $0.16 menjelang 2031, walaupun ada turun naik pasaran.",
            "translated_title": "",
            "translated_content": "",
            "translated_summary": "",
            "original_url": "https://coinmarketcap.com/community/en/articles/6510650807c57e0d185897b6",
            "source": "Cryptopolitan",
            "image": "https://www.cryptopolitan.com/wp-content/uploads/2024/12/VeChain-VET.webp",
            "fb_status": "Posted",
            "wp_status": "Skipped",
            "timestamp": "2025-04-23 20:15:00"
        },
        {
            "title": "Best Cryptos For Beginners: BTFD’s $6.56M Presale Nears End, $0.0002 Entry Fades Fast as PONKE Accelerates and ANDY Breaks Out on Ethereum",
            "translated_facebook_post": "Sekarang ni ada tiga matawang kripto menarik perhatian, iaitu BTFD, PONKE, dan ANDY.  BTFD dah hampir habis jualan awal, PONKE naik mendadak, manakala ANDY pun menunjukkan prestasi bagus.  Kalau nak masuk pasaran kripto, kena cepat!",
            "translated_title": "",
            "translated_content": "",
            "translated_summary": "",
            "original_url": "https://coinmarketcap.com/community/en/articles/68094b6528babe4022001e00",
            "source": "CoinoMedia",
            "image": "https://coinomedia.com/wp-content/uploads/2025/04/unnamed-97.png",
            "fb_status": "Posted",
            "wp_status": "Skipped",
            "timestamp": "2025-04-23 20:15:00"
        },
        {
            "title": "BTFD’s $0.0002 Entry, FINAL100 Bonus, and 2900% ROI Make $7K Flip to $420K Possible—6 Best New Meme Coins to Join This Month With BRETT and ...",
            "translated_facebook_post": "Beberapa syiling meme baharu, termasuk BTFD, BRETT, PNUT, FLOKI, POPCAT dan MOG, menawarkan potensi pulangan yang tinggi, tetapi BTFD menonjol dengan pra-jualan yang hampir tamat dan bonus tambahan.",
            "translated_title": "",
            "translated_content": "",
            "translated_summary": "",
            "original_url": "https://coinmarketcap.com/community/en/articles/68094b6628babe4022001e04",
            "source": "Kanal Coin",
            "image": "https://www.kanalcoin.com/wp-content/uploads/2025/04/2025-04-23T163326.786Zunnamed.png",
            "fb_status": "Posted",
            "wp_status": "Skipped",
            "timestamp": "2025-04-23 20:15:00"
        },
        {
            "title": "Avalanche breaks through resistance: is this the start of a rally to $28.70?",
            "translated_facebook_post": "Harga AVAX nampaknya dah patah rekod penurunan harga yang lama, dan mungkin akan naik sampai $28.70.",
            "translated_title": "",
            "translated_content": "",
            "translated_summary": "",
            "original_url": "https://coinmarketcap.com/community/en/articles/68094b657416902e68361054",
            "source": "crypto.news",
            "image": "https://crypto.news/app/uploads/2024/02/crypto-news-AVAX-Avalanche-option01.webp",
            "fb_status": "Posted",
            "wp_status": "Skipped",
            "timestamp": "2025-04-23 20:14:00"
        },
        {
            "title": "Trump Hosts Exclusive Dinner for Top TRUMP Token Holders",
            "translated_facebook_post": "Presiden Trump akan jamu makan malam eksklusif pemegang TRUMP token teratas, menyebabkan harga token melonjak 70%  —  satu lagi contoh bagaimana politik dan mata wang kripto boleh saling mempengaruhi.",
            "translated_title": "",
            "translated_content": "",
            "translated_summary": "",
            "original_url": "https://coinmarketcap.com/community/en/articles/68094b664eea9e3b10a482f3",
            "source": "TheCCPress",
            "image": "https://theccpress.com/wp-content/uploads/2025/04/trump-opulent-dinner-event.png",
            "fb_status": "Posted",
            "wp_status": "Skipped",
            "timestamp": "2025-04-23 20:12:00"
        },
        {
            "title": "Tired of Passive Projects Like BitTorrent and Akash? Dragoin’s Tap Game Pays You in $DDGN Before It Hits Exchanges",
            "translated_facebook_post": "Dragoin, satu projek kripto baru, tawarkan permainan di Telegram yang bagi ganjaran token $DDGN sebelum ia disenaraikan di bursa.  Berbeza dengan projek lain macam BitTorrent dan Akash yang kurang interaksi pengguna, Dragoin beri pengalaman  seronok dan untung dari awal.",
            "translated_title": "",
            "translated_content": "",
            "translated_summary": "",
            "original_url": "https://coinmarketcap.com/community/en/articles/68094b6578aaa619bb34d898",
            "source": "Coindoo",
            "image": "https://coindoo.com/wp-content/uploads/2025/04/dragoin-12309.webp",
            "fb_status": "Posted",
            "wp_status": "Skipped",
            "timestamp": "2025-04-23 20:10:00"
        },
        {
            "title": "INX Expands Trading with Polygon-USD Pair",
            "translated_facebook_post": "INX tambah pilihan dagangan dengan pasangan Polygon-USD, bagi memudahkan akses pasaran kripto dan mungkin tarik lebih ramai pelabur.",
            "translated_title": "",
            "translated_content": "",
            "translated_summary": "",
            "original_url": "https://coinmarketcap.com/community/en/articles/68094b6672206e3424b974a3",
            "source": "Kanal Coin",
            "image": "https://www.kanalcoin.com/wp-content/uploads/2025/04/polygon-usd-trading-office.png",
            "fb_status": "Posted",
            "wp_status": "Skipped",
            "timestamp": "2025-04-23 20:09:00"
        },
        {
            "title": "APT Thrives at Japan’s Expo 2025 Event",
            "translated_facebook_post": "Harga  meningkat hampir 9% dalam 24 jam lepas sebab  Aptos jadi dompet digital rasmi Expo 2025 di Osaka,  dengan jumlah transaksi dan pengguna baru yang banyak.",
            "translated_title": "",
            "translated_content": "",
            "translated_summary": "",
            "original_url": "https://en.bitcoinhaber.net/apt-thrives-at-japans-expo-2025-event",
            "source": "BH NEWS",
            "image": "https://en.bitcoinhaber.net/wp-content/uploads/2025/04/altcoin-091.jpg",
            "fb_status": "Posted",
            "wp_status": "Skipped",
            "timestamp": "2025-04-23 20:08:00"
        },
        {
            "title": "Alabama drops staking lawsuit against Coinbase",
            "translated_facebook_post": "Alabama dah tarik balik saman terhadap Coinbase, ikut jejak beberapa negeri lain yang dah buat benda sama sebab nak bagi ruang untuk pihak berkuasa persekutuan tetapkan peraturan untuk kripto dulu.",
            "translated_title": "Alabama menarik balik saman terhadap Coinbase.",
            "translated_content": "Suruhanjaya Sekuriti Alabama, pengawal selia kewangan bagi negeri AS itu, telah menggugurkan saman mereka terhadap bursa kripto Coinbase, yang menuduh syarikat itu melanggar undang-undang sekuriti dengan menawarkan perkhidmatan staking kepada pelanggan.\n\nPengawal selia tersebut memetik usaha berterusan antara Suruhanjaya Sekuriti dan Bursa AS (SEC) dan industri kripto untuk membangunkan peraturan kripto yang jelas sebagai sebab utama untuk menggugurkan litigasi tersebut, menurut pemfailan undang-undang pada 23 April yang dikongsi oleh ketua pegawai undang-undang Coinbase, Paul Grewal.\n\nPemfailan tersebut berbunyi:  \"Disebabkan perkara di atas, Suruhanjaya percaya adalah wajar untuk memberi masa kepada pembuat dasar untuk mempertimbangkan struktur pengawalseliaan,\" sambung pemfailan tersebut.\n\nSuruhanjaya Sekuriti Alabama memfailkan saman mereka terhadap Coinbase pada Jun 2023, bersama-sama pengawal selia negeri dari California, Illinois, Kentucky, Maryland, New Jersey, South Carolina, Vermont, Washington, dan Wisconsin.\n\nSamar yang digugurkan oleh Suruhanjaya itu mencerminkan perubahan pengawalseliaan positif terhadap mata wang kripto di Amerika Syarikat, memandangkan pembaharuan di peringkat persekutuan beralih kepada dasar pengawalseliaan peringkat negeri.\n\nLima daripada 10 negeri yang memfailkan litigasi terhadap Coinbase bagi perkhidmatan stakingnya telah menggugurkan saman mereka.\n\nPada 13 Mac, Jabatan Pengawalseliaan Kewangan Vermont menjadi yang pertama daripada 10 pengawal selia negeri untuk menggugurkan saman staking terhadap Coinbase.\n\nPengawal selia sekuriti South Carolina adalah yang seterusnya menggugurkan litigasi 2023 terhadap Coinbase, dengan membatalkan saman tersebut pada 28 Mac.\n\nGrewal mengumumkan bahawa Jabatan Institusi Kewangan Kentucky mengikut jejak Vermont dan South Carolina pada 1 April dengan juga membatalkan saman Coinbase mereka.\n\nWalaupun kesan domino negeri-negeri menarik balik litigasi terhadap bursa kripto itu, ketua pegawai undang-undang Coinbase berkata bahawa lebih banyak kerja perlu dilakukan.\n\n\"Lima negeri masih memilih untuk membazir sumber pembayar cukai pada saman, dan empat daripada negeri tersebut telah melarang staking dengan Coinbase, menafikan pengguna hak untuk memperoleh pendapatan pada platform pilihan mereka,\" tulis Grewal dalam catatan X pada 23 April.",
            "translated_summary": "Suruhanjaya Sekuriti Alabama secara rasminya menggugurkan saman 2023 mereka terhadap bursa Coinbase pada 23 April, satu kemenangan pengawalseliaan bagi…",
            "original_url": "https://coinmarketcap.com/community/en/articles/6809490c5bc5e763a9e85cc5",
            "source": "Cointelegraph.com News",
            "image": "https://images.cointelegraph.com/images/840_aHR0cHM6Ly9zMy5jb2ludGVsZWdyYXBoLmNvbS91cGxvYWRzLzIwMjUtMDEvMDE5NDkxMTItZDAwZi03MjNlLWJhMmYtOTVkNDcwNzcyODAw.jpg",
            "fb_status": "Posted",
            "wp_status": "Posted",
            "timestamp": "2025-04-23 20:08:00"
        },
        {
            "title": "A Trader Turns $173 into $224K on This Altcoin: Insider or Just Luck?",
            "translated_facebook_post": "Seseorang berjaya jana keuntungan besar, lebih RM900,000, daripada pelaburan kecil dalam altcoin TROLL cuma RM700.  Walaupun untung besar, pelaburan dalam mata wang kripto tetap berisiko tinggi.",
            "translated_title": "",
            "translated_content": "",
            "translated_summary": "",
            "original_url": "https://coinmarketcap.com/community/en/articles/6809490e5bc5e763a9e85ccb",
            "source": "Bitcoin Sistemi",
            "image": "https://www.bitcoinsistemi.com/wp-content/uploads/2023/06/kripto-para-cuzdan-soru-isareti.jpg",
            "fb_status": "Posted",
            "wp_status": "Skipped",
            "timestamp": "2025-04-23 20:07:00"
        },
        {
            "title": "Alabama Withdraws Enforcement Action Against Coinbase, Marking Significant Progress in Crypto Litigation",
            "translated_facebook_post": "Suruhanjaya Sekuriti Alabama dah tarik balik tindakan terhadap Coinbase pasal program staking, tinggal lima negeri je lagi yang masih bising.  Ini perkembangan positif untuk industri kripto, menunjukkan ada perubahan dalam hal pengurusan peraturan.",
            "translated_title": "",
            "translated_content": "",
            "translated_summary": "",
            "original_url": "https://coinmarketcap.com/community/en/articles/68094912891e88782de7c708",
            "source": "Coinstelegram",
            "image": "https://coinstelegram.com/wp-content/uploads/2025/04/POST-2025-04-23T220339.122-1-1.png",
            "fb_status": "Posted",
            "wp_status": "Skipped",
            "timestamp": "2025-04-23 20:05:00"
        },
        {
            "title": "BTC Rally Wipes $635M In Shorts Across Major Platforms",
            "translated_facebook_post": "Harga Bitcoin cecah $94,000, menyebabkan kerugian besar kepada pelabur yang ‘short sell’, dengan lebih $635 juta hilang dalam masa 24 jam.  Ramai jangka harga akan naik lagi mencecah $100,000.",
            "translated_title": "",
            "translated_content": "",
            "translated_summary": "",
            "original_url": "https://coinmarketcap.com/community/en/articles/68094b6678aaa619bb34d89a",
            "source": "Cointribune",
            "image": "https://www.cointribune.com/app/uploads/2025/04/SINAPI-738.png",
            "fb_status": "Posted",
            "wp_status": "Skipped",
            "timestamp": "2025-04-23 20:05:00"
        },
        {
            "title": "APT Soars with Major Activity at Expo 2025 in Japan",
            "translated_facebook_post": "Aptos (APT) makin naik harga lepas dapat jadi penyedia dompet digital untuk Expo 2025 di Jepun, dah cecah 9%!  Lebih 558,000 transaksi dan 133,000 akaun baru menunjukkan ramai dah guna.  Potensi untuk terus meningkat pun ada, tapi kena ingat, pasaran tetap boleh berubah.",
            "translated_title": "",
            "translated_content": "",
            "translated_summary": "",
            "original_url": "https://en.coin-turk.com/apt-soars-with-major-activity-at-expo-2025-in-japan/",
            "source": "COINTURK NEWS",
            "image": "https://en.coin-turk.com/wp-content/uploads/2025/04/altcoin-news-029.jpg",
            "fb_status": "Posted",
            "wp_status": "Skipped",
            "timestamp": "2025-04-23 20:01:00"
        },
        {
            "title": "BlockDAG Confirms Q3 Mainnet Launch with Audits, While Pi Network Eyes $2.10 and TRUMP Battles Liquidity Fears",
            "translated_facebook_post": "Pi Network nampaknya stabil lepas jatuh mendadak, ada harapan pulih perlahan.  TRUMP pula berdepan masalah lepas pengeluaran dana $4.6 juta, menjejaskan kepercayaan. BlockDAG pula fokus pelancaran Mainnet suku ketiga, dengan audit lengkap, nampak lebih kukuh.",
            "translated_title": "",
            "translated_content": "",
            "translated_summary": "",
            "original_url": "https://coinmarketcap.com/community/en/articles/6809076d24974405418589ee",
            "source": "CoinsProbe",
            "image": "https://academy-public.coinmarketcap.com/srd-optimized-uploads/bb97d943b354481e9176cc5a8f366990.png",
            "fb_status": "Posted",
            "wp_status": "Skipped",
            "timestamp": "2025-04-23 20:00:00"
        }
    ]
}