{
    "timestamp": "2025-05-21 16:34:19",
    "all_news": [
        {
            "title": "Binance Distributes Additional MERL Airdrop to Users",
            "translated_facebook_post": "Skipped",
            "translated_title": "",
            "translated_content": "",
            "translated_summary": "",
            "original_url": "https://coinmarketcap.com/community/en/articles/682dfe4eebdaba14a04fff8b",
            "source": "CoinLineup",
            "image": "https://coinlineup.com/wp-content/uploads/2025/05/binance-merl-airdrop-distribution.jpg",
            "fb_status": "Skipped",
            "wp_status": "Skipped",
            "timestamp": "2025-05-21 16:20:00"
        },
        {
            "title": "ECB Confident: Euro Zone Banks’ Dollar Exposure Secured by Fed Liquidity",
            "translated_facebook_post": "Skipped",
            "translated_title": "",
            "translated_content": "",
            "translated_summary": "",
            "original_url": "https://coinmarketcap.com/community/en/articles/682dfe4ce4049c24ac76a182",
            "source": "BitcoinWorld",
            "image": "https://bitcoinworld.co.in/wp-content/uploads/ecb-confident-euro-zone-banks-dollar-exposure-secured-by-fed-liquidity-900x600.webp",
            "fb_status": "Skipped",
            "wp_status": "Skipped",
            "timestamp": "2025-05-21 16:20:00"
        },
        {
            "title": "Avalanche price prediction 2025-2031: Time to buy AVAX?",
            "translated_facebook_post": "Skipped",
            "translated_title": "",
            "translated_content": "",
            "translated_summary": "",
            "original_url": "https://coinmarketcap.com/community/en/articles/64811eaa8e52bc5e90e9a8d9",
            "source": "Cryptopolitan",
            "image": "https://www.cryptopolitan.com/wp-content/uploads/2025/01/Avalanche-prediction.webp",
            "fb_status": "Skipped",
            "wp_status": "Skipped",
            "timestamp": "2025-05-21 16:20:00"
        },
        {
            "title": "Uniswap Lawsuit Dismissed: DeFi Giant Calls Bancor Claims ‘Meritless’ Amid US Crypto Scrutiny",
            "translated_facebook_post": "Skipped",
            "translated_title": "",
            "translated_content": "",
            "translated_summary": "",
            "original_url": "https://coinmarketcap.com/community/en/articles/682dfe4b466748478dadd04b",
            "source": "BitcoinWorld",
            "image": "https://bitcoinworld.co.in/wp-content/uploads/uniswap-lawsuit-dismissed-defi-giant-calls-bancor-claims-meritless-amid-us-crypto-scrutiny-900x600.webp",
            "fb_status": "Skipped",
            "wp_status": "Skipped",
            "timestamp": "2025-05-21 16:20:00"
        },
        {
            "title": "Shiba Inu (SHIB) Is About to Take off, Technical Analyst Says Don’t Miss the Chance",
            "translated_facebook_post": "Skipped",
            "translated_title": "",
            "translated_content": "",
            "translated_summary": "",
            "original_url": "https://coinmarketcap.com/community/en/articles/682dfd1f466748478dadd045",
            "source": "Crypto News - Latest Cryptocurrency News",
            "image": "https://timestabloid.com/wp-content/uploads/2023/05/Shiba-Inu-SHIB-Price1-300x200.jpg",
            "fb_status": "Skipped",
            "wp_status": "Skipped",
            "timestamp": "2025-05-21 16:18:00"
        },
        {
            "title": "Sovereign Wealth Funds Increase Bitcoin Holdings Significantly",
            "translated_facebook_post": "Skipped",
            "translated_title": "",
            "translated_content": "",
            "translated_summary": "",
            "original_url": "https://coinmarketcap.com/community/en/articles/682dfd20466748478dadd049",
            "source": "TheCCPress",
            "image": "https://theccpress.com/wp-content/uploads/2025/05/mubadala-bhutan-bitcoin-meetup.png",
            "fb_status": "Skipped",
            "wp_status": "Skipped",
            "timestamp": "2025-05-21 16:18:00"
        },
        {
            "title": "Bitcoin Dethrones Amazon as 5th Largest Asset–Is Apple Next?",
            "translated_facebook_post": "Bitcoin dah tawan Amazon sebagai aset ke-5 terbesar, dan mungkin akan mengatasi Apple jugak tak lama lagi, menandakan Bitcoin semakin kukuh dalam ekonomi dunia.",
            "translated_title": "",
            "translated_content": "",
            "translated_summary": "",
            "original_url": "https://coinmarketcap.com/community/en/articles/682dfd20b1116272a79cd547",
            "source": "The Crypto Times",
            "image": "https://www.cryptotimes.io/wp-content/uploads/2025/05/Bitcoin-Dethrones-Amazon-as-5th-Largest-Asset%E2%80%93Is-Apple-Next.jpg",
            "fb_status": "Failed",
            "wp_status": "Skipped",
            "timestamp": "2025-05-21 16:17:00"
        },
        {
            "title": "$2.5 Million Presale: Could Nexchain Be 2025-26’s Biggest Crypto Launch?",
            "translated_facebook_post": "Skipped",
            "translated_title": "",
            "translated_content": "",
            "translated_summary": "",
            "original_url": "https://coinmarketcap.com/community/en/articles/682dfd21b1116272a79cd549",
            "source": "36Crypto",
            "image": "https://i0.wp.com/36crypto.com/wp-content/uploads/2025/05/image1-35.webp",
            "fb_status": "Skipped",
            "wp_status": "Skipped",
            "timestamp": "2025-05-21 16:17:00"
        },
        {
            "title": "Russia Moves to Legalize Crypto Seizure in Crime Cases",
            "translated_facebook_post": "Skipped",
            "translated_title": "",
            "translated_content": "",
            "translated_summary": "",
            "original_url": "https://coinmarketcap.com/community/en/articles/682dfd21e4049c24ac76a17c",
            "source": "Coindoo",
            "image": "https://coindoo.com/wp-content/uploads/2025/03/bitcoinrussiabtc.jpeg",
            "fb_status": "Skipped",
            "wp_status": "Skipped",
            "timestamp": "2025-05-21 16:16:00"
        },
        {
            "title": "Bank lobby is 'panicking' about yield-bearing stablecoins — NYU professor",
            "translated_facebook_post": "Geng bank Amerika risau sebab duit stablecoin yang beri pulangan macam bagi faedah ni boleh kacau bisnes tradisional diorang.  Ramai dah keluarkan stablecoin macam ni, dan ini buat bank rasa terancam.",
            "translated_title": "Lobak bank ‘panik’ tentang stablecoin yang menjana hasil — Profesor NYU",
            "translated_content": "Amerika Syarikat sedang panik terhadap potensi stablecoin untuk mengganggu model perniagaan tradisional mereka, terutamanya melibatkan stablecoin yang menawarkan pulangan, menurut Austin Campbell, profesor Universiti New York dan pengasas Zero Knowledge Consulting.\n\nDalam catatan media sosial pada 21 Mei yang bermula dengan, “Empayar Melobi Kembali,” Campbell mendakwa bahawa industri perbankan amat bimbang dengan potensi stablecoin untuk menawarkan faedah atau ganjaran kepada pemegang.\n\nDalam mesej yang ditujukan kepada ahli-ahli perundangan Demokrat, Campbell menulis bahawa “bank-bank mahu anda melindungi kartel mereka supaya mereka boleh terus menipu pengundi anda.”\n\nBeliau menerangkan bagaimana perbankan rizab pecahan membolehkan bank memaksimumkan keuntungan sambil menawarkan faedah minimum kepada pendeposit.\n\nLobi perbankan mengatakan bahawa jika stablecoin membayar faedah atau apa-apa jenis ganjaran kewangan, bank akan “terjejas,” tambah Campbell.\n\n“Ini adalah rayuan terbuka untuk perlindungan kartel,” katanya sambil menggesa parti pembangkang untuk mengelakkan “menipu” pengundi mereka dengan menyokong sebarang jenis larangan menyeluruh terhadap pembayaran faedah stablecoin.\n\nCampbell telah lama menyokong perundangan stablecoin yang munasabah di Amerika Syarikat, memberi amaran kepada jawatankuasa kecil Kongres pada April 2023 bahawa kegagalan untuk menggubal undang-undang sedemikian akan mendorong penerbit ke luar negara.\n\nKemunculan stablecoin yang menawarkan pulangan\n\nPenilaian pedas Campbell terhadap industri perbankan tradisional muncul di tengah-tengah gelombang penerbit stablecoin yang melancarkan token yang menawarkan pulangan.\n\nSuruhanjaya Sekuriti dan Bursa AS (SEC) pada Februari meluluskan sekuriti stablecoin yang menawarkan pulangan pertama oleh Figure Markets. Pada masa pelancarannya, token YLDS baharu menawarkan pulangan 3.85%.\n\nFigure Markets bukanlah satu-satunya pemain yang menggunakan laluan stablecoin yang menawarkan pulangan.\n\nPada Februari, pengasas bersama Tether, Reeve Collins, mengumumkan bahawa Pi Protocolnya akan membenarkan pelabur mencetak stablecoin USP sebagai pertukaran untuk USI, bersamaan yang membayar faedah.\n\nUSDS Spark Protocol juga menawarkan pembayaran faedah kepada pemegang yang dijana melalui pinjaman terdesentralisasi dan Treasuri yang ditokenkan.\n\n“Adalah tidak boleh diterima untuk tidak menerima sekurang-kurangnya kadar bebas risiko untuk memegang stablecoin,” kata Sam MacPherson, Ketua Pegawai Eksekutif pembangun Spark Protocol, Phoenix Labs, kepada Bloomberg.\n\nSelain Bitcoin (BTC), stablecoin boleh dikatakan telah menjadi kes penggunaan teknologi blockchain yang paling berkesan, dengan Ketua Pegawai Eksekutif Coinbase Canada, Lucas Matheson, memberitahu Cointelegraph bahawa jumlah stablecoin global hampir tiga kali ganda daripada gergasi kad kredit Visa.",
            "translated_summary": "Lobis perbankan AS bimbang dengan peningkatan pesat stablecoin berpendapatan faedah, yang menurut mereka boleh mengganggu perbankan tradisional, menurut...",
            "original_url": "https://coinmarketcap.com/community/en/articles/682dfd20e4049c24ac76a17a",
            "source": "Cointelegraph.com News",
            "image": "https://images.cointelegraph.com/images/840_aHR0cHM6Ly9zMy5jb2ludGVsZWdyYXBoLmNvbS91cGxvYWRzLzIwMjUtMDEvMDE5NDRmNjAtZThjYy03MzFjLWE4ZDYtODA3MDEzYWU5MmRk.jpg",
            "fb_status": "Posted",
            "wp_status": "Posted",
            "timestamp": "2025-05-21 16:16:00"
        },
        {
            "title": "Dogecoin Whale Moves $92M As Analyst Predicts DOGE Price Rally to $0.27",
            "translated_facebook_post": "Skipped",
            "translated_title": "",
            "translated_content": "",
            "translated_summary": "",
            "original_url": "https://coinmarketcap.com/community/en/articles/682dfe4e466748478dadd04d",
            "source": "The Coin Republic",
            "image": "https://www.thecoinrepublic.com/wp-content/uploads/2025/05/Dogecoin-Whale-Moves-92M-As-Analyst-Predicts-DOGE-Price-Rally-to-0.27.jpg",
            "fb_status": "Skipped",
            "wp_status": "Skipped",
            "timestamp": "2025-05-21 16:16:00"
        },
        {
            "title": "Top 10 Meme Coins to Watch in May: Brett, Fartcoin, a Mystery Cat That’s Already Bagged $150K",
            "translated_facebook_post": "Beberapa duit syiling meme tengah naik sekarang, macam Troller Cat yang dah dapat kutip banyak duit dalam prajualan,  Brett, Gigachad, dan Melania pun nampak berpotensi.",
            "translated_title": "",
            "translated_content": "",
            "translated_summary": "",
            "original_url": "https://coinmarketcap.com/community/en/articles/682db85714e42024991e5f7b",
            "source": "Thecryptoupdates",
            "image": "https://academy-public.coinmarketcap.com/srd-optimized-uploads/5a7cecbe4f0647a090ec7633fe160fd4.jpg",
            "fb_status": "Posted",
            "wp_status": "Skipped",
            "timestamp": "2025-05-21 16:15:00"
        },
        {
            "title": "Asian Market Moves Signal New Growth—Qubetics, Polkadot, and Filecoin May Be the Best Altcoins to Invest in Now",
            "translated_facebook_post": "Skipped",
            "translated_title": "",
            "translated_content": "",
            "translated_summary": "",
            "original_url": "https://coinmarketcap.com/community/en/articles/682dfd1febdaba14a04fff83",
            "source": "Coindoo",
            "image": "https://coindoo.com/wp-content/uploads/2025/05/qubetics-wallet-where.webp",
            "fb_status": "Skipped",
            "wp_status": "Skipped",
            "timestamp": "2025-05-21 16:15:00"
        },
        {
            "title": "Why Qubetics, Arweave, and SUI Rank Among the Top Cryptos With 100x Potential",
            "translated_facebook_post": "Skipped",
            "translated_title": "",
            "translated_content": "",
            "translated_summary": "",
            "original_url": "https://coinmarketcap.com/community/en/articles/682dfd1febdaba14a04fff85",
            "source": "Crypto Front News",
            "image": "https://cryptofrontnews.com/wp-content/uploads/2025/05/unnamed-2025-05-20T194912.197-1.png",
            "fb_status": "Skipped",
            "wp_status": "Skipped",
            "timestamp": "2025-05-21 16:15:00"
        },
        {
            "title": "Top Crypto Gems to Buy in 2025: Qubetics, OKB, and Near Protocol Leading the Charge",
            "translated_facebook_post": "Skipped",
            "translated_title": "",
            "translated_content": "",
            "translated_summary": "",
            "original_url": "https://coinmarketcap.com/community/en/articles/682dfd20466748478dadd047",
            "source": "Kanal Coin",
            "image": "https://www.kanalcoin.com/wp-content/uploads/2025/05/2025-05-20T153532.254Zunnamed.png",
            "fb_status": "Skipped",
            "wp_status": "Skipped",
            "timestamp": "2025-05-21 16:15:00"
        },
        {
            "title": "Argentine President’s Move on LIBRA Probe Spurs Market Volatility Amid Legal Challenges",
            "translated_facebook_post": "Skipped",
            "translated_title": "",
            "translated_content": "",
            "translated_summary": "",
            "original_url": "https://coinmarketcap.com/community/en/articles/682dfd21ebdaba14a04fff87",
            "source": "ETHNews.com",
            "image": "https://www.ethnews.com/wp-content/uploads/2024/01/flag-of-argentina.jpeg",
            "fb_status": "Skipped",
            "wp_status": "Skipped",
            "timestamp": "2025-05-21 16:14:00"
        },
        {
            "title": "5 Best Cryptos to Buy Now Like BTFD, SLERF, and More—Claim 8900% Gains with LAUNCH200 Before May 26",
            "translated_facebook_post": "Beberapa kripto menarik perhatian sekarang, termasuk BTFD yang menawarkan pulangan tinggi dan ganjaran rujukan, serta beberapa lagi seperti BRETT, SLERF, BABYDOGE dan NPC.  Peluang pelaburan dalam BTFD dilihat menarik sebelum pelancarannya pada 27 Mei.",
            "translated_title": "",
            "translated_content": "",
            "translated_summary": "",
            "original_url": "https://coinmarketcap.com/community/en/articles/682db69f2e69270f48cd32e6",
            "source": "Thecryptoupdates",
            "image": "https://academy-public.coinmarketcap.com/srd-optimized-uploads/4bdb6c13b7cb458e8ced1f6c1c594a6f.jpg",
            "fb_status": "Posted",
            "wp_status": "Skipped",
            "timestamp": "2025-05-21 16:14:00"
        },
        {
            "title": "Is $8 Realistic? Ondo Price Prediction 2026 Strengthens as Qubetics Expands Web3 Wallet Access",
            "translated_facebook_post": "Ramalan harga Ondo Finance (ONDO) mencecah $8 pada 2026 nampaknya cerah, disokong pembangunan infrastruktur kewangan terdesentralisasi dan kerjasama dengan syarikat besar.  Pada masa sama, Qubetics dengan dompet pelbagai rantaiannya menawarkan utiliti segera kepada pengguna biasa, dan jualan awal yang memberangsangkan menjanjikan pulangan yang tinggi.  Kedua-dua projek ini memainkan peranan penting dalam pembangunan teknologi Web3.",
            "translated_title": "",
            "translated_content": "",
            "translated_summary": "",
            "original_url": "https://coinmarketcap.com/community/en/articles/682db4e514e42024991e5f68",
            "source": "Thecryptoupdates",
            "image": "https://academy-public.coinmarketcap.com/srd-optimized-uploads/705fff37d3544c67a204be920eedceb7.jpg",
            "fb_status": "Posted",
            "wp_status": "Skipped",
            "timestamp": "2025-05-21 16:12:00"
        }
    ]
}