{
    "timestamp": "2025-04-07 05:27:21",
    "all_news": [
        {
            "title": "MASSIVE SOLANA SOL UPDATE! Cardano ADA BREAKOUT?",
            "translated_facebook_post": "Solana tengah alami perubahan besar; walaupun memecoin dah tak sepopular dulu,  ETF Solana dapat perhatian SEC, mekanisme konsensus baru dalam pembangunan, dan ramai pemaju pindah dari Ethereum.  Tapi, ada juga risiko seperti pengeluaran token besar dan persaingan dari Cardano dan Sui.",
            "translated_title": "",
            "translated_content": "",
            "translated_summary": "",
            "original_url": "https://coinmarketcap.com/community/en/articles/67f35e036177b415a8643e2c",
            "source": "Altcoin Buzz",
            "image": "https://s2.coinmarketcap.com/static/img/coins/200x200/2010.png",
            "fb_status": "Failed",
            "wp_status": "Skipped",
            "timestamp": "2025-04-07 05:08:00"
        },
        {
            "title": "Cango Inc. Achieves 12% Growth in Bitcoin Production for March 2025",
            "translated_facebook_post": "Syarikat Cango berjaya meningkatkan pengeluaran Bitcoin sebanyak 12% pada Mac 2025, mencapai 530.1 Bitcoin, dan kini memegang sejumlah 2,474.8 Bitcoin.",
            "translated_title": "",
            "translated_content": "",
            "translated_summary": "",
            "original_url": "https://coinmarketcap.com/community/en/articles/67f35e071fd75c2a0b4b0579",
            "source": "BitcoinWorld",
            "image": "https://bitcoinworld.co.in/wp-content/uploads/005-18.jpg",
            "fb_status": "Failed",
            "wp_status": "Skipped",
            "timestamp": "2025-04-07 05:07:00"
        },
        {
            "title": "200,000 Ethereum Addresses Now Hold Stablecoins: Why Is This So Important?",
            "translated_facebook_post": "Lebih 200,000 akaun Ethereum sekarang guna stablecoin, menandakan ekosistem kripto makin matang dan stabil, walaupun harga Ethereum sendiri turun naik.",
            "translated_title": "",
            "translated_content": "",
            "translated_summary": "",
            "original_url": "https://coinmarketcap.com/community/en/articles/67f35e053702e825e4e20146",
            "source": "Cointribune",
            "image": "https://www.cointribune.com/app/uploads/2025/04/ethereum-stablecoins.png",
            "fb_status": "Failed",
            "wp_status": "Skipped",
            "timestamp": "2025-04-07 05:05:00"
        },
        {
            "title": "Bitcoin CME Futures Gap Lower After Trump Says 'There Won't Be a Deal With China'",
            "translated_facebook_post": "Bitcoin CME Futures jatuh selepas Trump kata tiada perjanjian dengan China. Trump, bila ditanya pasal pasaran saham yang jatuh, cakap kadang-kadang kita kena \"makan ubat\".\n\n\nHarga Bitcoin turun sebab Trump cakap takkan ada perjanjian perdagangan dengan China.",
            "translated_title": "",
            "translated_content": "",
            "translated_summary": "",
            "original_url": "https://coinmarketcap.com/headlines/news/bitcoin-cme-futures-gap-lower-after-trump-says-there-won-t-be-a-deal-with-china/",
            "source": "CoinDesk",
            "image": "https://cdn.sanity.io/images/s3y3vcno/production/51240ca7505138f3787d40792e08f451c0ac1445-1634x968.png",
            "fb_status": "Failed",
            "wp_status": "Skipped",
            "timestamp": "2025-04-07 05:03:00"
        },
        {
            "title": "50x Still Possible? Solana, BTC, and XRP Aren’t Done Yet",
            "translated_facebook_post": "Solana, BTC, XRP masih berpotensi naik, disokong  juga oleh ETH, LINK, HBAR, dan satu lagi projek baru, MAGACOINFINANCE yang tengah naik.  Peluang masih ada.",
            "translated_title": "",
            "translated_content": "",
            "translated_summary": "",
            "original_url": "https://coinmarketcap.com/community/en/articles/67f35cf23702e825e4e20141",
            "source": "Bitcoin Sistemi",
            "image": "https://en.bitcoinsistemi.com/wp-content/uploads/2025/04/17439505516816051-image4.png",
            "fb_status": "Failed",
            "wp_status": "Skipped",
            "timestamp": "2025-04-07 05:02:00"
        },
        {
            "title": "Bitcoin falls below $80K after brief resilience amid Trump tariff jitters",
            "translated_facebook_post": "Harga Bitcoin jatuh bawah $80,000 selepas kejatuhan pasaran saham global susulan pengumuman tarif import baharu oleh Presiden Trump.  Pasaran kripto turut terjejas teruk, dengan ramai pelabur bimbang akan perang perdagangan dan kemelesetan ekonomi.",
            "translated_title": "",
            "translated_content": "",
            "translated_summary": "",
            "original_url": "https://coinmarketcap.com/community/en/articles/67f35cf03702e825e4e20139",
            "source": "crypto.news",
            "image": "https://crypto.news/app/uploads/2025/04/crypto-news-Miners-win-most-from-the-US-strategic-Bitcoin-reserve-option04.webp",
            "fb_status": "Failed",
            "wp_status": "Skipped",
            "timestamp": "2025-04-07 05:00:00"
        },
        {
            "title": "$60K or $78K? All Paths Lead to $125K Bitcoin",
            "translated_facebook_post": "Ramai pakar jangka harga Bitcoin akan naik sampai $125,000 walaupun mungkin akan turun sikit dulu ke $78,000, $72,000, atau $60,000.",
            "translated_title": "",
            "translated_content": "",
            "translated_summary": "",
            "original_url": "https://coinmarketcap.com/community/en/articles/67f35cf03702e825e4e2013b",
            "source": "CoinoMedia",
            "image": "https://coinomedia.com/wp-content/uploads/2025/04/CoinoMedia-2-1.jpg",
            "fb_status": "Failed",
            "wp_status": "Skipped",
            "timestamp": "2025-04-07 05:00:00"
        },
        {
            "title": "McGregor Token Misses Fundraising Goal as Meme Coin Momentum Slows",
            "translated_facebook_post": "Token Conor McGregor, REAL, tak capai sasaran dana, menunjukkan minat pelabur terhadap aset kripto spekulatif semakin berkurangan.  Walaupun begitu, pedagang berpengalaman masih nampak aktif dalam pasaran meme coin, cuma lebih berhati-hati.",
            "translated_title": "",
            "translated_content": "",
            "translated_summary": "",
            "original_url": "https://coinmarketcap.com/community/en/articles/67f35cf01fd75c2a0b4b0577",
            "source": "Coinpaper",
            "image": "https://res.coinpaper.com/coinpaper/f_webp,c_limit,w_1080,q_auto:good/cp6225_empty_bags_of_money_in_a_UFC_ring_46f9ccd9_0d95_4a00_a468_3f326c7c02c6_8ab6075110.webp",
            "fb_status": "Failed",
            "wp_status": "Skipped",
            "timestamp": "2025-04-07 05:00:00"
        },
        {
            "title": "Mantle Network Plans Q1 2025 Upgrade for Enhanced Performance",
            "translated_facebook_post": "Rangkaian Mantle akan naik taraf sistem di suku pertama 2025 untuk tingkatkan prestasi dan kecekapan, dijangka menarik lebih ramai pembangun dan pengguna.",
            "translated_title": "",
            "translated_content": "",
            "translated_summary": "",
            "original_url": "https://coinmarketcap.com/community/en/articles/67f35cf13702e825e4e2013d",
            "source": "Kanal Coin",
            "image": "https://www.kanalcoin.com/wp-content/uploads/2025/04/futuristic-cityscape-2025-news.png",
            "fb_status": "Failed",
            "wp_status": "Skipped",
            "timestamp": "2025-04-07 04:59:00"
        },
        {
            "title": "Chinese and Taiwanese Stock Markets Experience Sharp Declines Amid U.S. Tariff Impacts",
            "translated_facebook_post": "Pasaran saham China dan Taiwan jatuh mendadak disebabkan tarif AS, menjejaskan syarikat teknologi besar dan menampakkan kelemahan rantaian bekalan global.",
            "translated_title": "",
            "translated_content": "",
            "translated_summary": "",
            "original_url": "https://coinmarketcap.com/community/en/articles/67f35bc03702e825e4e20137",
            "source": "TheCCPress",
            "image": "https://theccpress.com/wp-content/uploads/2025/04/abstract-stock-indices-oil-painting.png",
            "fb_status": "Failed",
            "wp_status": "Skipped",
            "timestamp": "2025-04-07 04:57:00"
        },
        {
            "title": "Dogecoin Prepares for Q2 Breakout as Whale Accumulation Hits 6-Month High",
            "translated_facebook_post": "Nampaknya Dogecoin macam nak naik balik ni, ramai yang tengah kumpul sekarang, siap cecah paras tertinggi dalam 6 bulan.  Kalau ikut trend sebelum ni, mungkin ada potensi untuk harga dia meningkat lagi menjelang suku kedua tahun depan. Tapi kena ingat,  pelaburan dalam matawang kripto ni tetap berisiko tinggi.",
            "translated_title": "",
            "translated_content": "",
            "translated_summary": "",
            "original_url": "https://coinmarketcap.com/community/en/articles/67f35a363702e825e4e20134",
            "source": "Cryptos Newss",
            "image": "https://academy-public.coinmarketcap.com/srd-optimized-uploads/361215f5528a486898d8e026a2ae4f4a.png",
            "fb_status": "Failed",
            "wp_status": "Skipped",
            "timestamp": "2025-04-07 04:54:00"
        },
        {
            "title": "Missed Just a Chill Guy? This Hidden Star Is the Best Crypto Project to Watch Now",
            "translated_facebook_post": "Kalau terlepas peluang ‘Just a Chill Guy’,  ‘Troller Cat’ nampaknya peluang kedua untuk dapatkan keuntungan awal dalam dunia kripto.",
            "translated_title": "",
            "translated_content": "",
            "translated_summary": "",
            "original_url": "https://coinmarketcap.com/community/en/articles/67f2e01de3266c17ba9d0ff5",
            "source": "CoinsProbe",
            "image": "https://academy-public.coinmarketcap.com/srd-optimized-uploads/b77fc6cc98944cb4be15534d432d2a57.png",
            "fb_status": "Failed",
            "wp_status": "Skipped",
            "timestamp": "2025-04-07 04:45:00"
        },
        {
            "title": "Troller Cat Claws Its Way to the Top Amid Positive Vibes from Simon’s Cat and Ponke",
            "translated_facebook_post": "Troller Cat,  bersama Simon’s Cat dan Ponke, tengah hangat dalam dunia mata wang kripto.  Pelabur berebut peluang dapat keuntungan besar dengan  Troller Cat sebab  ganjaran staking tinggi dan  Game Center main-untuk-dapat.  Keunikan ini mungkin ubah landskap mata wang kripto.",
            "translated_title": "",
            "translated_content": "",
            "translated_summary": "",
            "original_url": "https://coinmarketcap.com/community/en/articles/67f35a984ba542289cef2c1b",
            "source": "Crypto Front News",
            "image": "https://cryptofrontnews.com/wp-content/uploads/2025/04/unnamed-2025-04-06T204053.193-1.png",
            "fb_status": "Failed",
            "wp_status": "Skipped",
            "timestamp": "2025-04-07 04:45:00"
        },
        {
            "title": "XRP Could Jump to $27: A Deep Dive into 3 Fib Levels",
            "translated_facebook_post": "Ramalan harga XRP boleh meningkat sehingga $27 berdasarkan paras Fibonacci dan corak carta sejarah. Kemenangan Ripple terhadap SEC dan peningkatan penggunaan oleh institusi menyumbang kepada potensi kenaikan ini.",
            "translated_title": "",
            "translated_content": "",
            "translated_summary": "",
            "original_url": "https://cryptonewsland.com/xrp-could-jump-to-27/",
            "source": "CryptoNewsLand",
            "image": "https://cryptonewsland.com/wp-content/uploads/2024/07/xrp-coin-15.jpg",
            "fb_status": "Failed",
            "wp_status": "Skipped",
            "timestamp": "2025-04-07 04:40:00"
        },
        {
            "title": "APT, MOVE, MOCA, XTER: Over $96M Tokens to Unlock",
            "translated_facebook_post": "Lebih RM400 juta token akan dikeluarkan untuk APT, MOVE, MOCA, dan XTER menjelang 12 April, mungkin akan menjejaskan pasaran.",
            "translated_title": "",
            "translated_content": "",
            "translated_summary": "",
            "original_url": "https://coinmarketcap.com/community/en/articles/67f358284ba542289cef2c16",
            "source": "Coincu",
            "image": "https://coincu.com/wp-content/uploads/2025/04/aptos-token-unlock-thumbnail.png",
            "fb_status": "Failed",
            "wp_status": "Skipped",
            "timestamp": "2025-04-07 04:39:00"
        },
        {
            "title": "Crypto Market Crash Today: $985M Liquidated, Bitcoin Dips Below $78K; XRP, SOL And ETH Down 15%",
            "translated_facebook_post": "Translation failed",
            "translated_title": "",
            "translated_content": "",
            "translated_summary": "",
            "original_url": "https://coinmarketcap.com/community/en/articles/67f358274ba542289cef2c12",
            "source": "CoinPedia News",
            "image": "https://image.coinpedia.org/wp-content/uploads/2025/02/19191842/298M-Liquidated-in-Crypto-Bloodbath-as-Bitcoin-Price-Dips-Is-the-Bull-Run-Over.webp",
            "fb_status": "Skipped",
            "wp_status": "Skipped",
            "timestamp": "2025-04-07 04:39:00"
        },
        {
            "title": "Global retaliation against US tariffs is expected this week",
            "translated_facebook_post": "Pasaran saham Amerika jatuh teruk sebab dasar tarif Trump, dan banyak negara bakal balas dengan tarif mereka sendiri.  Ini mungkin akan menyebabkan kemelesetan ekonomi global.",
            "translated_title": "",
            "translated_content": "",
            "translated_summary": "",
            "original_url": "https://coinmarketcap.com/community/en/articles/67f358273702e825e4e20130",
            "source": "Cryptopolitan",
            "image": "https://www.cryptopolitan.com/wp-content/uploads/2025/04/Trump-6.webp",
            "fb_status": "Failed",
            "wp_status": "Skipped",
            "timestamp": "2025-04-07 04:36:00"
        },
        {
            "title": "Accelerating Asia Names Zen Rooms' Tanna as Mentor",
            "translated_facebook_post": "Amit Tanna dari Zen Rooms sekarang mentor untuk syarikat-syarikat baru di Accelerating Asia, bagi membantu mereka maju dan berinovasi.",
            "translated_title": "",
            "translated_content": "",
            "translated_summary": "",
            "original_url": "https://coinmarketcap.com/community/en/articles/67f357034ba542289cef2c0e",
            "source": "Kanal Coin",
            "image": "https://www.kanalcoin.com/wp-content/uploads/2025/04/amit-tanna-mentoring-startups.png",
            "fb_status": "Failed",
            "wp_status": "Skipped",
            "timestamp": "2025-04-07 04:35:00"
        },
        {
            "title": "Tariff News Sparks Massive Market Sell-Off in Asia",
            "translated_facebook_post": "Cukai import baru Amerika Syarikat menyebabkan pasaran saham di Asia jatuh mendadak, dengan Taiwan bertindak pantas untuk menstabilkan keadaan dan China turut terkesan.",
            "translated_title": "",
            "translated_content": "",
            "translated_summary": "",
            "original_url": "https://coinmarketcap.com/community/en/articles/67f355e44ba542289cef2c09",
            "source": "TheCCPress",
            "image": "https://theccpress.com/wp-content/uploads/2025/04/stock-market-turmoil-oil-painting.png",
            "fb_status": "Failed",
            "wp_status": "Skipped",
            "timestamp": "2025-04-07 04:33:00"
        }
    ]
}