{
    "timestamp": "2025-05-16 09:28:43",
    "all_news": [
        {
            "title": "Hyperliquid Slipped Through the Cracks — Qubetics Emerges as the Most Popular Cryptocurrency Opportunity of 2025",
            "translated_facebook_post": "Skipped",
            "translated_title": "",
            "translated_content": "",
            "translated_summary": "",
            "original_url": "https://coinmarketcap.com/community/en/articles/68270278877fe266eaea2646",
            "source": "Optimisus",
            "image": "https://academy-public.coinmarketcap.com/srd-optimized-uploads/2bb32933eae343bba4923489f3da9378.jpg",
            "fb_status": "Skipped",
            "wp_status": "Skipped",
            "timestamp": "2025-05-16 09:16:00"
        },
        {
            "title": "Abu Dhabi Fund Expands Bitcoin Holdings with IBIT",
            "translated_facebook_post": "Skipped",
            "translated_title": "",
            "translated_content": "",
            "translated_summary": "",
            "original_url": "https://coinmarketcap.com/community/en/articles/6827033b877fe266eaea2651",
            "source": "CoinLineup",
            "image": "https://coinlineup.com/wp-content/uploads/2025/05/abu-dhabi-fund-bitcoin-expansion.jpg",
            "fb_status": "Skipped",
            "wp_status": "Skipped",
            "timestamp": "2025-05-16 09:16:00"
        },
        {
            "title": "Binance’s CZ Shares Urgent Security Advice to Combat Phishing Threats",
            "translated_facebook_post": "Skipped",
            "translated_title": "",
            "translated_content": "",
            "translated_summary": "",
            "original_url": "https://coinmarketcap.com/community/en/articles/6827033bfb9fa014d63f6d06",
            "source": "Coindoo",
            "image": "https://coindoo.com/wp-content/uploads/2025/04/IMAGE-2025-04-12-182220.jpg",
            "fb_status": "Skipped",
            "wp_status": "Skipped",
            "timestamp": "2025-05-16 09:16:00"
        },
        {
            "title": "Northern Mariana Islands passes bill to issue government-backed MUSD stablecoin",
            "translated_facebook_post": "Skipped",
            "translated_title": "",
            "translated_content": "",
            "translated_summary": "",
            "original_url": "https://coinmarketcap.com/community/en/articles/68270339fb9fa014d63f6cfa",
            "source": "crypto.news",
            "image": "https://crypto.news/app/uploads/2025/03/cropped-crypto-news-Stablecoins-can-hold-central-banks-fiscally-accountable-option03.webp",
            "fb_status": "Skipped",
            "wp_status": "Skipped",
            "timestamp": "2025-05-16 09:15:00"
        },
        {
            "title": "Bitcoin Surges Past $105,000 Amid Institutional Growth",
            "translated_facebook_post": "Skipped",
            "translated_title": "",
            "translated_content": "",
            "translated_summary": "",
            "original_url": "https://coinmarketcap.com/community/en/articles/6827033ad3d8b1750e8157b0",
            "source": "Bitcoin Info News",
            "image": "https://bitcoininfonews.com/wp-content/uploads/2025/05/futuristic-city-night-bitcoin-art.png.jpg",
            "fb_status": "Skipped",
            "wp_status": "Skipped",
            "timestamp": "2025-05-16 09:15:00"
        },
        {
            "title": "Bitcoin’s 2025 Cycle Begins Strong with $102K Candle: Why $285K Is the Next Target",
            "translated_facebook_post": "Skipped",
            "translated_title": "",
            "translated_content": "",
            "translated_summary": "",
            "original_url": "https://coinmarketcap.com/community/en/articles/68270339877fe266eaea264b",
            "source": "Crypto Front News",
            "image": "https://cryptofrontnews.com/wp-content/uploads/2024/11/BITCOIN-1.jpg",
            "fb_status": "Skipped",
            "wp_status": "Skipped",
            "timestamp": "2025-05-16 09:15:00"
        },
        {
            "title": "Here’s what Polymarket thinks about the next cryptocurrency cycle",
            "translated_facebook_post": "Skipped",
            "translated_title": "",
            "translated_content": "",
            "translated_summary": "",
            "original_url": "https://coinmarketcap.com/community/en/articles/682703393d4fd70a6082f671",
            "source": "crypto.news",
            "image": "https://crypto.news/app/uploads/2024/07/crypto-news-What-is-Polymarket-option03.webp",
            "fb_status": "Skipped",
            "wp_status": "Skipped",
            "timestamp": "2025-05-16 09:14:00"
        },
        {
            "title": "Bitcoin Solaris: The Fast, Green Future of Crypto Payments",
            "translated_facebook_post": "Bitcoin Solaris, projek kripto baru, gabung keselamatan Bitcoin dengan kelajuan Solana,  proses transaksi ribuan sesaat, cuma 2 saat siap. Guna kuasa rendah, sesuai untuk pembayaran harian,  boleh `mining` guna telefon, dan ada ciri DeFi. Peluang untung lumayan untuk pelabur awal.",
            "translated_title": "",
            "translated_content": "",
            "translated_summary": "",
            "original_url": "https://coinmarketcap.com/community/en/articles/682701e9d3d8b1750e8157ab",
            "source": "Coin_Gabbar",
            "image": "https://academy-public.coinmarketcap.com/srd-optimized-uploads/aa2acf172e2f4947b6e657141251b9bc.jpg",
            "fb_status": "Posted",
            "wp_status": "Skipped",
            "timestamp": "2025-05-16 09:14:00"
        },
        {
            "title": "WEMIX Trading Suspended on Major Korean Exchanges",
            "translated_facebook_post": "Skipped",
            "translated_title": "",
            "translated_content": "",
            "translated_summary": "",
            "original_url": "https://coinmarketcap.com/community/en/articles/6827033afb9fa014d63f6d00",
            "source": "Kanal Coin",
            "image": "https://www.kanalcoin.com/wp-content/uploads/2025/05/busy-korea-street-wemix-alert.png",
            "fb_status": "Skipped",
            "wp_status": "Skipped",
            "timestamp": "2025-05-16 09:11:00"
        },
        {
            "title": "Google has announced changes to Android: Here are 8 that you will find exciting",
            "translated_facebook_post": "Skipped",
            "translated_title": "",
            "translated_content": "",
            "translated_summary": "",
            "original_url": "https://coinmarketcap.com/community/en/articles/68270338d3d8b1750e8157ae",
            "source": "Technext",
            "image": "https://s2.coinmarketcap.com/static/img/coins/200x200/7682.png",
            "fb_status": "Skipped",
            "wp_status": "Skipped",
            "timestamp": "2025-05-16 09:10:00"
        },
        {
            "title": "DOJ indicts 12 more in $236M crypto crime ring",
            "translated_facebook_post": "Skipped",
            "translated_title": "",
            "translated_content": "",
            "translated_summary": "",
            "original_url": "https://coinmarketcap.com/community/en/articles/68270339fb9fa014d63f6cfc",
            "source": "Cryptopolitan",
            "image": "https://www.cryptopolitan.com/wp-content/uploads/2025/05/DOJ-crypto-crime-ring.webp",
            "fb_status": "Skipped",
            "wp_status": "Skipped",
            "timestamp": "2025-05-16 09:10:00"
        },
        {
            "title": "DeFi Trends: Unlocking Astonishing Opportunities in Decentralized Finance",
            "translated_facebook_post": "Skipped",
            "translated_title": "",
            "translated_content": "",
            "translated_summary": "",
            "original_url": "https://coinmarketcap.com/community/en/articles/6827033a877fe266eaea264d",
            "source": "BitcoinWorld",
            "image": "https://bitcoinworld.co.in/wp-content/uploads/DeFi-Trends-Unlocking-Astonishing-Opportunities-in-Decentralized-Finance.webp",
            "fb_status": "Skipped",
            "wp_status": "Skipped",
            "timestamp": "2025-05-16 09:10:00"
        },
        {
            "title": "Here is why Bitcoin price is stuck below $105K",
            "translated_facebook_post": "Harga Bitcoin masih tak boleh pecah paras $105,000 sebab ada halangan di situ, dan setakat ini belum ada apa-apa yang boleh dorong harga naik dengan mendadak.  Walaupun ramai agak negatif, sejarah menunjukkan harga mungkin boleh naik secara tiba-tiba.  Beberapa pakar juga kata paras sokongan penting perlu diperhatikan untuk jangka masa panjang.",
            "translated_title": "Inilah sebabnya harga Bitcoin masih di bawah $105,000",
            "translated_content": "**Intip Utama:**\n\nHarga Bitcoin berlegar dalam julat sekitar $105,000, menghalang kenaikan ke paras tertinggi sepanjang zaman baharu.  Peniaga agak bearish, tetapi data sejarah menunjukkan pergerakan menaik secara tiba-tiba tidak boleh dikesampingkan.\n\nHarga Bitcoin (BTC) telah berlegar dalam lingkungan kira-kira $3,500 sepanjang tujuh hari yang lalu, dengan paras $105,000 kekal sebagai rintangan utama yang perlu diatasi.\n\n**Bitcoin Gagal Pecah Paras $105,000**\n\nData daripada Cointelegraph Markets Pro dan Bitstamp menunjukkan harga BTC berayun antara paras rintangannya pada $105,000 dan $101,500, di mana ia menemui sokongan.  \"BTC tersekat dalam julat penyempitan $101.5K–$104K,\" kata Swissblock dalam catatan pada 16 Mei di X. Penyedia data onchain itu berkata Bitcoin mula berlegar selepas dua percubaan gagal untuk memecah paras rintangan pada $105,000.\n\nBagi firma perisikan pasaran Santiment, kegagalan untuk meningkat melepasi paras $105,000 telah menyebabkan peniaga beralih sedikit kepada sentimen bearish.  Firma itu menjelaskan dalam catatan X, bahawa pasaran amnya cenderung bergerak bertentangan dengan jangkaan ramai, menunjukkan kebarangkalian tinggi pasaran kripto meningkat disebabkan peningkatan ketakutan ini.\n\nHarga Bitcoin kekurangan \"pemacu utama\"\n\nBitcoin berjaya mengekalkan $100,000 sebagai sokongan selama lebih seminggu sambil mencecah paras tertinggi 14 minggu iaitu $105,700 pada 12 Mei. Walaupun mengikuti turun naik yang meluas merentas aset berisiko, BTC/USD mungkin telah meningkat lebih tinggi jika bukan kerana tindakan entiti perdagangan volum besar dalam buku pesanan bursa, menurut sumber dagangan Material Indicators.\n\nMelihat bursa Binance, Material Indicators berhujah bahawa blok besar kecairan permintaan disusun di atas harga spot, mengekang harga BTC dalam julat. Carta yang disertakan menunjukkan bahawa kelompok kecairan ini kini berada di antara $105,000 dan $110,000.  Satu paras utama untuk diperhatikan di bahagian bawah ialah julat $98,000-$100,000.\n\n**Pendukung Bitcoin Berjuang untuk Mengekalkan Paras Sokongan Utama**\n\nSementara itu, peniaga popular Daan Crypto Trades berkata bahawa \"permulaan pergerakan baru-baru ini\" pada $93,000 adalah penting untuk peniaga Bitcoin pada masa hadapan.  Material Indicators juga memberi perhatian tambahan kepada purata bergerak mudah (SMA) 50 hari dan 100 hari, garis arah aliran jangka panjang utama yang membentuk persilangan menaik, menunjukkan \"momentum menaik yang kukuh untuk trend makro.\"  Bagi pengasas MN Capital, Michael van de Poppe, $98,000 adalah \"kawasan penting untuk dikekalkan\" untuk memastikan kesinambungan ke atas.\n\n*Artikel ini tidak mengandungi nasihat atau cadangan pelaburan. Setiap pergerakan pelaburan dan perdagangan melibatkan risiko, dan pembaca harus menjalankan kajian mereka sendiri semasa membuat keputusan.*",
            "translated_summary": "Pergerakan harga Bitcoin yang terhenti adalah disebabkan oleh rintangan pada paras $105,000 dan ketiadaan pemangkin yang jelas untuk memecahkannya daripada pengukuhan.",
            "original_url": "https://coinmarketcap.com/community/en/articles/6827033afb9fa014d63f6cfe",
            "source": "Cointelegraph.com News",
            "image": "https://images.cointelegraph.com/images/840_aHR0cHM6Ly9zMy5jb2ludGVsZWdyYXBoLmNvbS91cGxvYWRzLzIwMjUtMDUvMDE5NmQ4NGItODFkZC03MmM0LWFjZjItNDRiZTI3YThmMGNi.jpg",
            "fb_status": "Posted",
            "wp_status": "Posted",
            "timestamp": "2025-05-16 09:09:00"
        },
        {
            "title": "Dave Portnoy Now Backs XRP: “Meme Coins Won’t Last, It’s Gambling”",
            "translated_facebook_post": "Dave Portnoy, dah tak minat ‘meme coin’ sebab rasa macam perjudian je, sekarang lebih suka XRP sebab nampak potensi untuk naik harga macam Bitcoin dulu.  Dia sendiri akui lebih kepada ikut ‘feeling’ dan peluang untung besar, bukan analisis teknikal.",
            "translated_title": "",
            "translated_content": "",
            "translated_summary": "",
            "original_url": "https://coinmarketcap.com/community/en/articles/68270339877fe266eaea2649",
            "source": "CoinPedia News",
            "image": "https://image.coinpedia.org/wp-content/uploads/2025/05/13194409/NYC-Mayor-Criticizes-Memecoins-Ahead-of-Crypto-Summit.webp",
            "fb_status": "Posted",
            "wp_status": "Skipped",
            "timestamp": "2025-05-16 09:09:00"
        },
        {
            "title": "Here is Why XRP Price is Crashing Today",
            "translated_facebook_post": "Skipped",
            "translated_title": "",
            "translated_content": "",
            "translated_summary": "",
            "original_url": "https://coinmarketcap.com/community/en/articles/682700e33d4fd70a6082f66e",
            "source": "36Crypto",
            "image": "https://i0.wp.com/36crypto.com/wp-content/uploads/2025/05/xrp-price-prediction-111-convert.io_.webp",
            "fb_status": "Skipped",
            "wp_status": "Skipped",
            "timestamp": "2025-05-16 09:08:00"
        },
        {
            "title": "Bitcoin Price Prediction As Crypto Fear and Greed Index Hits 69",
            "translated_facebook_post": "Pasaran kripto macam turun sikit hari ni, Bitcoin dekat $103,922.  Ada analisis menunjukkan Bitcoin susah nak tembus $105,000, mungkin jatuh ke $100,000, tapi kalau berjaya, boleh cecah $110,000.  Secara keseluruhannya, pasaran masih kukuh walaupun ada sedikit penurunan dalam beberapa altcoin.",
            "translated_title": "",
            "translated_content": "",
            "translated_summary": "",
            "original_url": "https://coinmarketcap.com/community/en/articles/682700e1fb9fa014d63f6cf8",
            "source": "CoinPedia News",
            "image": "https://image.coinpedia.org/wp-content/uploads/2024/09/06131920/Crypto-Price-Today-Bitcoins-Fear-and-Greed-Index-Hits-Extreme-Low-Whats-Next.webp",
            "fb_status": "Posted",
            "wp_status": "Skipped",
            "timestamp": "2025-05-16 09:08:00"
        },
        {
            "title": "Altcoin Boom: Investors Shift Focus as Crypto Market Rebounds",
            "translated_facebook_post": "Skipped",
            "translated_title": "",
            "translated_content": "",
            "translated_summary": "",
            "original_url": "https://coinmarketcap.com/community/en/articles/6827033afb9fa014d63f6d04",
            "source": "Cointribune",
            "image": "https://www.cointribune.com/app/uploads/2025/05/crypto-interet-croissant-pour-altcoins-1.png",
            "fb_status": "Skipped",
            "wp_status": "Skipped",
            "timestamp": "2025-05-16 09:05:00"
        },
        {
            "title": "US picks Pakistan over India in Crypto power play",
            "translated_facebook_post": "Skipped",
            "translated_title": "",
            "translated_content": "",
            "translated_summary": "",
            "original_url": "https://coinmarketcap.com/community/en/articles/6827033a3d4fd70a6082f673",
            "source": "Todayq News",
            "image": "https://news.todayq.com/wp-content/uploads/2025/05/Untitled-17-1.jpg",
            "fb_status": "Skipped",
            "wp_status": "Skipped",
            "timestamp": "2025-05-16 09:04:00"
        },
        {
            "title": "Trends and Innovations in the Digital Currency Marketplace",
            "translated_facebook_post": "Skipped",
            "translated_title": "",
            "translated_content": "",
            "translated_summary": "",
            "original_url": "https://coinmarketcap.com/community/en/articles/682700e1fb9fa014d63f6cf6",
            "source": "Altcoin Buzz",
            "image": "https://s2.coinmarketcap.com/static/img/coins/200x200/28847.png",
            "fb_status": "Skipped",
            "wp_status": "Skipped",
            "timestamp": "2025-05-16 09:04:00"
        }
    ]
}