{
    "timestamp": "2025-04-17 18:36:03",
    "all_news": [
        {
            "title": "Slovenia Considers 25% Tax on Crypto Gains for Individuals",
            "translated_facebook_post": "Kerajaan Slovenia nak kenakan cukai 25% ke atas keuntungan kripto individu, mungkin akan ubah strategi pelabur dan daya saing pasaran.",
            "translated_title": "",
            "translated_content": "",
            "translated_summary": "",
            "original_url": "https://coinmarketcap.com/community/en/articles/6801479bc257d1436c5d0fe1",
            "source": "Bitcoin Info News",
            "image": "https://bitcoininfonews.com/wp-content/uploads/2025/04/pixelated-financial-traders.jpg.jpg",
            "fb_status": "Posted",
            "wp_status": "Skipped",
            "timestamp": "2025-04-17 18:21:00"
        },
        {
            "title": "VALR Launches DeFi Lending, Expanding Crypto Yield Opportunities",
            "translated_facebook_post": "VALR, bursa kripto terbesar di Afrika,  lancar perkhidmatan pinjaman DeFi, bagi pengguna akses peluang pulangan kripto dengan lebih mudah.  Pengguna boleh pinjam aset kripto dan dapat ganjaran setiap jam.  Ciri ini akan ada juga di aplikasi mudah alih nanti.",
            "translated_title": "",
            "translated_content": "",
            "translated_summary": "",
            "original_url": "https://coinmarketcap.com/community/en/articles/6801475964538561a7f35b6f",
            "source": "Crypto.ro",
            "image": "https://crypto.ro/en/wp-content/uploads/2025/04/photo_2025-01-27_15-07-02_17448794776maJdmuVuH-1024x574.jpg",
            "fb_status": "Posted",
            "wp_status": "Skipped",
            "timestamp": "2025-04-17 18:21:00"
        },
        {
            "title": "Trump’s Stance on Powell Sends Bitcoin Prices Soaring",
            "translated_facebook_post": "Harga Bitcoin melonjak sebab Trump tak puas hati dengan Powell, tapi jangka panjang mungkin tak berapa elok untuk mata wang kripto.",
            "translated_title": "",
            "translated_content": "",
            "translated_summary": "",
            "original_url": "https://en.coin-turk.com/trumps-stance-on-powell-sends-bitcoin-prices-soaring/",
            "source": "COINTURK NEWS",
            "image": "https://en.coin-turk.com/wp-content/uploads/2025/04/economy-014.jpg",
            "fb_status": "Posted",
            "wp_status": "Skipped",
            "timestamp": "2025-04-17 18:20:00"
        },
        {
            "title": "LayerZero's ZRO Jumps 10% as VC Firm Andreessen Horowitz Buys $55M Worth",
            "translated_facebook_post": "Firma modal usaha niaga, Andreessen Horowitz, telah membeli ZRO bernilai $55 juta, menyebabkan harga ZRO melonjak 10%.  Ini susulan pelaburan-pelaburan terdahulu mereka dalam protokol tersebut.\n\n\nHarga ZRO naik 10% lepas Andreessen Horowitz beli banyak, menunjukkan keyakinan pelabur terhadap projek ni.",
            "translated_title": "",
            "translated_content": "",
            "translated_summary": "",
            "original_url": "https://coinmarketcap.com/headlines/news/layerzero-s-zro-jumps-10-as-vc-firm-andreessen-horowitz-buys-usd55m-worth/",
            "source": "CoinDesk",
            "image": "https://cdn.sanity.io/images/s3y3vcno/production/d397a5b2187b1314592d32d1567ff593c30134e6-2869x1614.jpg",
            "fb_status": "Posted",
            "wp_status": "Skipped",
            "timestamp": "2025-04-17 18:18:00"
        },
        {
            "title": "Ex-SEC Chief Gensler Predicts Prosperity for Bitcoin and Doom for Altcoins",
            "translated_facebook_post": "Bekas ketua SEC, Gary Gensler, jangka Bitcoin akan terus maju, tapi duit kripto lain mungkin akan jatuh.  Dia nampak Bitcoin unik macam emas,  sedangkan kebanyakan duit kripto lain terlalu bergantung pada spekulasi dan trend, jadi tak bertahan lama.",
            "translated_title": "",
            "translated_content": "",
            "translated_summary": "",
            "original_url": "https://coinmarketcap.com/community/en/articles/68014645b516c245e5002d7f",
            "source": "Coinpaper",
            "image": "https://res.coinpaper.com/coinpaper/f_webp,c_limit,w_1080,q_auto:good/gary1704_91b5b2f699.webp",
            "fb_status": "Posted",
            "wp_status": "Skipped",
            "timestamp": "2025-04-17 18:18:00"
        },
        {
            "title": "Panama City Approves Crypto for Tax Payments",
            "translated_facebook_post": "Majlis Bandaraya Panama City dah benarkan pembayaran cukai guna kripto, kerjasama dengan bank untuk tukar kepada USD.  Ini mungkin akan galakkan lebih ramai orang guna kripto dan jadi contoh untuk bandar-bandar lain.",
            "translated_title": "",
            "translated_content": "",
            "translated_summary": "",
            "original_url": "https://coinmarketcap.com/community/en/articles/6801464717cb1d26f736de31",
            "source": "CoinLive.me",
            "image": "https://coinlive.me/wp-content/uploads/2025/04/panama-city-crypto-inkscape.png",
            "fb_status": "Posted",
            "wp_status": "Skipped",
            "timestamp": "2025-04-17 18:18:00"
        },
        {
            "title": "Skipped FLOKI? Don’t Sleep on Arctic Pablo—One of the Top New Meme Coins to Invest in This Week",
            "translated_facebook_post": "Pelaburan dalam mata wang kripto seperti Arctic Pablo memang berisiko, tapi potensi keuntungannya juga tinggi, jadi kena buat kajian sendiri sebelum melabur.",
            "translated_title": "",
            "translated_content": "",
            "translated_summary": "",
            "original_url": "https://coinmarketcap.com/community/en/articles/6801419964538561a7f35b64",
            "source": "36Crypto",
            "image": "https://i0.wp.com/36crypto.com/wp-content/uploads/2025/04/image2-12.webp",
            "fb_status": "Posted",
            "wp_status": "Skipped",
            "timestamp": "2025-04-17 18:15:00"
        },
        {
            "title": "Will You Seize the Crypto Throne? Arctic Pablo Coin’s $0.10 Forecast Sets the Stage for Massive ROI as Popcat and Brett Coin Blaze Ahead",
            "translated_facebook_post": "Pelaburan awal dalam Arctic Pablo Coin nampaknya berpotensi pulangan tinggi, berbanding Popcat dan Brett Coin.",
            "translated_title": "",
            "translated_content": "",
            "translated_summary": "",
            "original_url": "https://cryptonewsland.com/will-you-seize-the-crypto-throne-arctic-pablo-coins-0-10-forecast-sets-the-stage-for-massive-roi-as-popcat-and-brett-coin-blaze-ahead/",
            "source": "CryptoNewsLand",
            "image": "https://cryptonewsland.com/wp-content/uploads/2025/04/unnamed-93-1.png",
            "fb_status": "Posted",
            "wp_status": "Skipped",
            "timestamp": "2025-04-17 18:15:00"
        },
        {
            "title": "Ethereum Nears $1,600 Support – Could 2025 See Another Historic Rally",
            "translated_facebook_post": "Harga Ethereum hampir mencecah paras sokongan RM6,900, dan sejarah menunjukkan ia mungkin akan melonjak naik lagi menjelang 2025.",
            "translated_title": "",
            "translated_content": "",
            "translated_summary": "",
            "original_url": "https://coinmarketcap.com/community/en/articles/6801464517cb1d26f736de2f",
            "source": "Crypto Front News",
            "image": "https://cryptofrontnews.com/wp-content/uploads/2024/11/ethereum-2-1.jpg",
            "fb_status": "Posted",
            "wp_status": "Skipped",
            "timestamp": "2025-04-17 18:15:00"
        },
        {
            "title": "Trump Criticizes Powell, Calls for Lower Interest Rates",
            "translated_facebook_post": "Presiden Trump kritik tindakan pengerusi Rizab Persekutuan, desak kadar faedah diturunkan.  Pasaran kewangan dan kripto bertindak balas, Bitcoin naik sedikit.  Ada spekulasi dasar monetari lebih longgar mungkin bantu pasaran kripto.",
            "translated_title": "",
            "translated_content": "",
            "translated_summary": "",
            "original_url": "https://coinmarketcap.com/community/en/articles/6801451764538561a7f35b6b",
            "source": "Coincu",
            "image": "https://coincu.com/wp-content/uploads/2025/04/trump-powell-cartoon-debate.png",
            "fb_status": "Posted",
            "wp_status": "Skipped",
            "timestamp": "2025-04-17 18:12:00"
        },
        {
            "title": "Gary Gensler Returns, Tariffs vs Crypto ETFs, + Worst is Over?",
            "translated_facebook_post": "Bekas pengerusi SEC, Gary Gensler, bimbang strategi tarif agresif Trump boleh menjejaskan pasaran AS dan hubungan diplomatik dengan China, tetapi pasaran kripto nampaknya menunjukkan tanda-tanda positif dengan penurunan tarif.",
            "translated_title": "",
            "translated_content": "",
            "translated_summary": "",
            "original_url": "https://coinmarketcap.com/community/en/articles/680143ebb516c245e5002d79",
            "source": "PBN3",
            "image": "https://s2.coinmarketcap.com/static/img/coins/200x200/27251.png",
            "fb_status": "Posted",
            "wp_status": "Skipped",
            "timestamp": "2025-04-17 18:05:00"
        },
        {
            "title": "XRP price surges, using XRP on Blockchain Cloud Mining to make $7788a day",
            "translated_facebook_post": "Harga XRP melonjak tinggi, peluang untung lumayan dengan platform BlockchainCloudMining.  Daftar mudah, pelaburan rendah, dan pulangan harian menarik.",
            "translated_title": "",
            "translated_content": "",
            "translated_summary": "",
            "original_url": "https://coinmarketcap.com/community/en/articles/680143ee64538561a7f35b68",
            "source": "BitcoinWorld",
            "image": "https://bitcoinworld.co.in/wp-content/uploads/image1-45.jpg",
            "fb_status": "Posted",
            "wp_status": "Skipped",
            "timestamp": "2025-04-17 18:05:00"
        },
        {
            "title": "Binance Advises Countries On Creating Bitcoin Reserves, Says Its CEO",
            "translated_facebook_post": "Binance tengah bantu beberapa kerajaan wujudkan simpanan Bitcoin strategik dan rangka kerja kawal selia, ikut jejak Amerika.",
            "translated_title": "",
            "translated_content": "",
            "translated_summary": "",
            "original_url": "https://coinmarketcap.com/community/en/articles/680143edb516c245e5002d7b",
            "source": "Cointribune",
            "image": "https://www.cointribune.com/app/uploads/2025/04/binance-bitcoin-etats.png",
            "fb_status": "Posted",
            "wp_status": "Skipped",
            "timestamp": "2025-04-17 18:05:00"
        },
        {
            "title": "Binance Labs Becomes Initia's Leading Investor",
            "translated_facebook_post": "Binance Labs jadi pelabur utama Initia yang berjaya kumpul dana $24 juta dalam pusingan pendanaan pra-biji benih, sekaligus melonjakkan nilai syarikat kepada $350 juta untuk memudahkan lagi teknologi blockchain.",
            "translated_title": "",
            "translated_content": "",
            "translated_summary": "",
            "original_url": "https://coinmarketcap.com/community/en/articles/680142c1c257d1436c5d0fda",
            "source": "TokenTopNews",
            "image": "https://tokentopnews.com/wp-content/uploads/2025/04/initia-secures-24m-funding.png",
            "fb_status": "Posted",
            "wp_status": "Skipped",
            "timestamp": "2025-04-17 18:02:00"
        },
        {
            "title": "XRP Beats Ethereum for 6 Months Straight – Will XRP Become Next Largest Altcoin?",
            "translated_facebook_post": "XRP dah pukul Ethereum selama 6 bulan, harga dia naik mendadak lepas kes mahkamah dengan SEC selesai.  Ramai pun yakin XRP akan jadi altcoin kedua terbesar sebab ramai beli lepas dapat berita baik tu, tambah pula dengan kemungkinan ETF XRP diluluskan.",
            "translated_title": "",
            "translated_content": "",
            "translated_summary": "",
            "original_url": "https://coinmarketcap.com/community/en/articles/680142c0b516c245e5002d75",
            "source": "CoinPedia News",
            "image": "https://image.coinpedia.org/wp-content/uploads/2024/08/06165059/xrp-eth.webp",
            "fb_status": "Posted",
            "wp_status": "Skipped",
            "timestamp": "2025-04-17 18:01:00"
        },
        {
            "title": "Analysts Predict Strong 2025 for BTC, ETH, and XRP—Up to 1,500 Percent",
            "translated_facebook_post": "Ramai pakar jangka Bitcoin, Ethereum, dan XRP akan naik mendadak sampai 1500 peratus menjelang 2025, tapi satu lagi pelaburan, MAGACOINFINANCE, dijangka bagi pulangan yang lebih tinggi dan pantas.",
            "translated_title": "",
            "translated_content": "",
            "translated_summary": "",
            "original_url": "https://www.ethnews.com/analysts-predict-strong-2025-for-btc-eth-and-xrp-up-to-1500-percent/",
            "source": "ETHNews.com",
            "image": "https://www.ethnews.com/wp-content/uploads/2025/04/unnamed-2025-04-17T193520.439.png",
            "fb_status": "Posted",
            "wp_status": "Skipped",
            "timestamp": "2025-04-17 18:00:00"
        },
        {
            "title": "Crypto Traders Flips $4.5K Into $666K Overnight—But Was It Insider Trading?",
            "translated_facebook_post": "Beberapa pelabur kripto untung besar, tukar pelaburan kecil jadi ratusan ribu ringgit dalam masa beberapa jam, tapi ramai syak berlaku perdagangan dalam kalangan orang tertentu.",
            "translated_title": "",
            "translated_content": "",
            "translated_summary": "",
            "original_url": "https://coinmarketcap.com/community/en/articles/680142c0c257d1436c5d0fd8",
            "source": "Coindoo",
            "image": "https://coindoo.com/wp-content/uploads/2025/04/crypto-trade-win-money-profit.webp",
            "fb_status": "Posted",
            "wp_status": "Skipped",
            "timestamp": "2025-04-17 18:00:00"
        },
        {
            "title": "Top Analyst Predicts April Breakout for XRP, Reveals Key Levels and Targets",
            "translated_facebook_post": "Pakar analisis jangka harga  bagi XRP ramal kenaikan mendadak mungkin berlaku hujung April ini, dengan sasaran harga sehingga mencecah $9.50.",
            "translated_title": "",
            "translated_content": "",
            "translated_summary": "",
            "original_url": "https://coinmarketcap.com/community/en/articles/680142c0c257d1436c5d0fd6",
            "source": "Captain Altcoin",
            "image": "https://captainaltcoin.com/wp-content/uploads/2023/10/xrp-ratio-1-300x175.png",
            "fb_status": "Posted",
            "wp_status": "Skipped",
            "timestamp": "2025-04-17 18:00:00"
        },
        {
            "title": "Pumpdotfun Co-Founder Denies Imminent Token Launch",
            "translated_facebook_post": "Pengasas bersama Pumpdotfun menafikan khabar angin pelancaran token, tumpuan tetap pada pembangunan platform, jadi tak perlu risau sangat.",
            "translated_title": "",
            "translated_content": "",
            "translated_summary": "",
            "original_url": "https://coinmarketcap.com/community/en/articles/6801419cc257d1436c5d0fd2",
            "source": "TheCCPress",
            "image": "https://theccpress.com/wp-content/uploads/2025/04/alon-cohen-modern-office-portrait.png",
            "fb_status": "Posted",
            "wp_status": "Skipped",
            "timestamp": "2025-04-17 17:57:00"
        },
        {
            "title": "Shiba Inu on Cross Roads Will SHIB Price Hit $0.000020 Mark?",
            "translated_facebook_post": "Harga Shiba Inu agak tak menentu sekarang,  naik turun dalam lingkungan 2% setiap hari sejak beberapa hari lepas. Walaupun ada tanda-tanda positif macam  pergerakan harga membentuk corak menurun dan indikator teknikal menunjukkan potensi kenaikan,  risiko penurunan harga masih ada.  Masa depan SHIB masih belum pasti.",
            "translated_title": "",
            "translated_content": "",
            "translated_summary": "",
            "original_url": "https://coinmarketcap.com/community/en/articles/6801419cb516c245e5002d73",
            "source": "The Crypto Times",
            "image": "https://www.cryptotimes.io/wp-content/uploads/2025/04/Shiba-Inu-on-Cross-Roads-Will-SHIB-Price-Hit-0.000020-Mark.png",
            "fb_status": "Posted",
            "wp_status": "Skipped",
            "timestamp": "2025-04-17 17:53:00"
        }
    ]
}